phoenixdb/__init__.py
phoenixdb/connection.py
phoenixdb/cursor.py
phoenixdb/errors.py
phoenixdb/meta.py
phoenixdb/sqlalchemy_phoenix.py
phoenixdb/types.py
phoenixdb/avatica/__init__.py
phoenixdb/avatica/client.py
phoenixdb/avatica/proto/__init__.py
phoenixdb/avatica/proto/common_pb2.py
phoenixdb/avatica/proto/requests_pb2.py
phoenixdb/avatica/proto/responses_pb2.py
phoenixdb/tests/__init__.py
phoenixdb/tests/dbapi20.py
phoenixdb/tests/test_avatica.py
phoenixdb/tests/test_db.py
phoenixdb/tests/test_dbapi20.py
phoenixdb/tests/test_errors.py
phoenixdb/tests/test_sqlalchemy.py
phoenixdb/tests/test_types.py
phoenixdb-1.2.2.dist-info/LICENSE
phoenixdb-1.2.2.dist-info/METADATA
phoenixdb-1.2.2.dist-info/NOTICE
phoenixdb-1.2.2.dist-info/WHEEL
phoenixdb-1.2.2.dist-info/entry_points.txt
phoenixdb-1.2.2.dist-info/top_level.txt
phoenixdb-1.2.2.dist-info/RECORD
