Metadata-Version: 2.1
Name: phoenixdb
Version: 1.2.2
Summary: Phoenix database adapter for Python
Home-page: http://phoenix.apache.org/python.html
Author: Apache Software Foundation
Author-email: dev@phoenix.apache.org
License: Apache 2
Platform: UNKNOWN
Classifier: Programming Language :: Python
Classifier: Programming Language :: Python :: 2
Classifier: Programming Language :: Python :: 2.7
Classifier: Programming Language :: Python :: 3
Classifier: Programming Language :: Python :: 3.5
Classifier: Programming Language :: Python :: 3.6
Classifier: Programming Language :: Python :: 3.7
Classifier: Programming Language :: Python :: 3.8
Classifier: Programming Language :: Python :: 3.9
Classifier: Programming Language :: Python :: 3.10
Classifier: Programming Language :: Python :: 3.11
Classifier: Programming Language :: Python :: 3.12
Requires-Dist: protobuf (>=3.0.0)
Requires-Dist: requests
Requires-Dist: gssapi (<1.6.0) ; python_version < "3.6.0"
Requires-Dist: requests-gssapi (<1.3.0) ; python_version < "3.8.0"
Requires-Dist: requests-gssapi ; python_version >= "3.8.0"
